edgetpu_dfs/__init__.py
edgetpu_dfs/dfs_interface.py
edgetpu_dfs/dfs_utils.py
edgetpu_dfs/pci_dfs_manager.py
edgetpu_dfs/pci_dfs_manager_with_trip_point.py
edgetpu_dfs/usb_dfs_manager.py
edgetpu_dfs-0.3.0.dist-info/licenses/LICENSE
third_party/libedgetpu/rename_library.py
edgetpu_dfs-0.3.0.dist-info/METADATA
edgetpu_dfs-0.3.0.dist-info/WHEEL
edgetpu_dfs-0.3.0.dist-info/top_level.txt
edgetpu_dfs-0.3.0.dist-info/RECORD
