Metadata-Version: 2.4
Name: edgetpu-dfs
Version: 0.3.0
Summary: A utility tool to set the Edge TPU DFS performance
Author-email: Changhun Han <ehwjs1914@naver.com>
License: MIT License
Classifier: Programming Language :: Python :: 3
Classifier: Operating System :: OS Independent
Classifier: License :: OSI Approved :: MIT License
Requires-Python: >=3.9
License-File: LICENSE
Dynamic: license-file
